gaycore/__init__.py
gaycore/__main__.py
gaycore/cli.py
gaycore/config.py
gaycore/gcore_box.py
gaycore/player.py
gaycore/utils.py
gaycore-4.0.dist-info/licenses/LICENSE
gaycore-4.0.dist-info/METADATA
gaycore-4.0.dist-info/WHEEL
gaycore-4.0.dist-info/entry_points.txt
gaycore-4.0.dist-info/top_level.txt
gaycore-4.0.dist-info/zip-safe
gaycore-4.0.dist-info/RECORD
