Metadata-Version: 2.4
Name: gaycore
Version: 4.0
Summary: A tiny and smart cli player of gcore audio, based on Python package curses and mpg123 for Linux or Mac
Home-page: https://github.com/yihong0618/gaycore
Author: yihong0618
Author-email: yihong0618 <zouzou0208@gmail.com>
License: MIT
Requires-Python: >=3.10
License-File: LICENSE
Requires-Dist: requests
Requires-Dist: miservice-fork
Requires-Dist: curl-cffi>=0.14.0
Dynamic: author
Dynamic: home-page
Dynamic: license-file
Dynamic: requires-python
